{"start": {"connected": [{"socket": 8, "local_host": "192.168.218.235", "local_port": 35618, "remote_host": "192.168.218.238", "remote_port": 5201}, {"socket": 10, "local_host": "192.168.218.235", "local_port": 35620, "remote_host": "192.168.218.238", "remote_port": 5201}], "version": "iperf 3.1.3", "system_info": "Linux hera 4.15.0-55-generic #60-Ubuntu SMP Tue Jul 2 18:22:20 UTC 2019 x86_64", "timestamp": {"time": "Sun, 11 Aug 2019 19:49:01 GMT", "timesecs": 1565552941}, "connecting_to": {"host": "192.168.218.238", "port": 5201}, "cookie": "hera.1565552941.874039.0648ad5a40ec0", "tcp_mss_default": 1448, "test_start": {"protocol": "TCP", "num_streams": 2, "blksize": 8192, "omit": 0, "duration": 20, "bytes": 0, "blocks": 0, "reverse": 0}}, "intervals": [{"streams": [{"socket": 8, "start": 0, "end": 1.000044, "seconds": 1.000044, "bytes": 60083616, "bits_per_second": 480647842.450881, "retransmits": 11, "snd_cwnd": 362000, "rtt": 3448, "omitted": false}, {"socket": 10, "start": 0, "end": 1.000054, "seconds": 1.000054, "bytes": 43057328, "bits_per_second": 344440064.674158, "retransmits": 10, "snd_cwnd": 250504, "rtt": 3530, "omitted": false}], "sum": {"start": 0, "end": 1.000044, "seconds": 1.000044, "bytes": 103140944, "bits_per_second": 825091356.051992, "retransmits": 21, "omitted": false}}, {"streams": [{"socket": 8, "start": 1.000044, "end": 2.000466, "seconds": 1.000422, "bytes": 66273280, "bits_per_second": 529962595.315755, "retransmits": 0, "snd_cwnd": 467704, "rtt": 2991, "omitted": false}, {"socket": 10, "start": 1.000054, "end": 2.000477, "seconds": 1.000423, "bytes": 38221808, "bits_per_second": 305645189.973365, "retransmits": 1, "snd_cwnd": 272224, "rtt": 2761, "omitted": false}], "sum": {"start": 1.000044, "end": 2.000466, "seconds": 1.000422, "bytes": 104495088, "bits_per_second": 835608076.652131, "retransmits": 1, "omitted": false}}, {"streams": [{"socket": 8, "start": 2.000466, "end": 3.000399, "seconds": 0.999933, "bytes": 61685760, "bits_per_second": 493519143.621368, "retransmits": 29, "snd_cwnd": 415576, "rtt": 3236, "omitted": false}, {"socket": 10, "start": 2.000477, "end": 3.00041, "seconds": 0.999933, "bytes": 42500248, "bits_per_second": 340024764.170138, "retransmits": 1, "snd_cwnd": 273672, "rtt": 3600, "omitted": false}], "sum": {"start": 2.000466, "end": 3.000399, "seconds": 0.999933, "bytes": 104186008, "bits_per_second": 833543907.791506, "retransmits": 30, "omitted": false}}, {"streams": [{"socket": 8, "start": 3.000399, "end": 4.000416, "seconds": 1.000017, "bytes": 60538880, "bits_per_second": 484302726.392713, "retransmits": 10, "snd_cwnd": 377928, "rtt": 2385, "omitted": false}, {"socket": 10, "start": 3.00041, "end": 4.000427, "seconds": 1.000017, "bytes": 42807224, "bits_per_second": 342451913.4233, "retransmits": 9, "snd_cwnd": 282360, "rtt": 2255, "omitted": false}], "sum": {"start": 3.000399, "end": 4.000416, "seconds": 1.000017, "bytes": 103346104, "bits_per_second": 826754639.816013, "retransmits": 19, "omitted": false}}, {"streams": [{"socket": 8, "start": 4.000416, "end": 5.000687, "seconds": 1.000271, "bytes": 57999360, "bits_per_second": 463869244.027687, "retransmits": 7, "snd_cwnd": 363448, "rtt": 3024, "omitted": false}, {"socket": 10, "start": 4.000427, "end": 5.0007, "seconds": 1.000273, "bytes": 45755352, "bits_per_second": 365942917.508964, "retransmits": 12, "snd_cwnd": 301184, "rtt": 3177, "omitted": false}], "sum": {"start": 4.000416, "end": 5.000687, "seconds": 1.000271, "bytes": 103754712, "bits_per_second": 829812946.552348, "retransmits": 19, "omitted": false}}, {"streams": [{"socket": 8, "start": 5.000687, "end": 6.000424, "seconds": 0.999737, "bytes": 54968320, "bits_per_second": 439862233.075457, "retransmits": 9, "snd_cwnd": 348968, "rtt": 3862, "omitted": false}, {"socket": 10, "start": 5.0007, "end": 6.000435, "seconds": 0.999735, "bytes": 46679176, "bits_per_second": 373532439.465694, "retransmits": 9, "snd_cwnd": 304080, "rtt": 3785, "omitted": false}], "sum": {"start": 5.000687, "end": 6.000424, "seconds": 0.999737, "bytes": 101647496, "bits_per_second": 813393870.816656, "retransmits": 18, "omitted": false}}, {"streams": [{"socket": 8, "start": 6.000424, "end": 7.000404, "seconds": 0.99998, "bytes": 54558720, "bits_per_second": 436478501.425066, "retransmits": 20, "snd_cwnd": 340280, "rtt": 2991, "omitted": false}, {"socket": 10, "start": 6.000435, "end": 7.000415, "seconds": 0.99998, "bytes": 48668728, "bits_per_second": 389357621.727638, "retransmits": 14, "snd_cwnd": 312768, "rtt": 3029, "omitted": false}], "sum": {"start": 6.000424, "end": 7.000404, "seconds": 0.99998, "bytes": 103227448, "bits_per_second": 825836123.152704, "retransmits": 34, "omitted": false}}, {"streams": [{"socket": 8, "start": 7.000404, "end": 8.000383, "seconds": 0.999979, "bytes": 57180160, "bits_per_second": 457450877.701368, "retransmits": 34, "snd_cwnd": 309872, "rtt": 2775, "omitted": false}, {"socket": 10, "start": 7.000415, "end": 8.000395, "seconds": 0.99998, "bytes": 47365528, "bits_per_second": 378931812.928291, "retransmits": 13, "snd_cwnd": 209960, "rtt": 3030, "omitted": false}], "sum": {"start": 7.000404, "end": 8.000383, "seconds": 0.999979, "bytes": 104545688, "bits_per_second": 836383052.014778, "retransmits": 47, "omitted": false}}, {"streams": [{"socket": 8, "start": 8.000383, "end": 9.000536, "seconds": 1.000153, "bytes": 57125392, "bits_per_second": 456933195.644794, "retransmits": 1, "snd_cwnd": 306976, "rtt": 3310, "omitted": false}, {"socket": 10, "start": 8.000395, "end": 9.000548, "seconds": 1.000153, "bytes": 46952704, "bits_per_second": 375564146.37617, "retransmits": 0, "snd_cwnd": 325800, "rtt": 3523, "omitted": false}], "sum": {"start": 8.000383, "end": 9.000536, "seconds": 1.000153, "bytes": 104078096, "bits_per_second": 832497342.020963, "retransmits": 1, "omitted": false}}, {"streams": [{"socket": 8, "start": 9.000536, "end": 10.0005, "seconds": 0.999964, "bytes": 50558368, "bits_per_second": 404481505.82179, "retransmits": 8, "snd_cwnd": 318560, "rtt": 3203, "omitted": false}, {"socket": 10, "start": 9.000548, "end": 10.000512, "seconds": 0.999964, "bytes": 53329920, "bits_per_second": 426654720.084232, "retransmits": 21, "snd_cwnd": 328696, "rtt": 3519, "omitted": false}], "sum": {"start": 9.000536, "end": 10.0005, "seconds": 0.999964, "bytes": 103888288, "bits_per_second": 831136225.906021, "retransmits": 29, "omitted": false}}, {"streams": [{"socket": 8, "start": 10.0005, "end": 11.000497, "seconds": 0.999997, "bytes": 51412688, "bits_per_second": 411302778.808913, "retransmits": 11, "snd_cwnd": 320008, "rtt": 2810, "omitted": false}, {"socket": 10, "start": 10.000512, "end": 11.000509, "seconds": 0.999997, "bytes": 53329920, "bits_per_second": 426640580.628492, "retransmits": 11, "snd_cwnd": 328696, "rtt": 2703, "omitted": false}], "sum": {"start": 10.0005, "end": 11.000497, "seconds": 0.999997, "bytes": 104742608, "bits_per_second": 837943461.156762, "retransmits": 22, "omitted": false}}, {"streams": [{"socket": 8, "start": 11.000497, "end": 12.000397, "seconds": 0.9999, "bytes": 44557560, "bits_per_second": 356496093.027329, "retransmits": 2, "snd_cwnd": 321456, "rtt": 4010, "omitted": false}, {"socket": 10, "start": 11.000509, "end": 12.000408, "seconds": 0.999899, "bytes": 58900480, "bits_per_second": 471251478.565758, "retransmits": 31, "snd_cwnd": 301184, "rtt": 3875, "omitted": false}], "sum": {"start": 11.000497, "end": 12.000397, "seconds": 0.9999, "bytes": 103458040, "bits_per_second": 827747009.761422, "retransmits": 33, "omitted": false}}, {"streams": [{"socket": 8, "start": 12.000397, "end": 13.001333, "seconds": 1.000936, "bytes": 46842480, "bits_per_second": 374389399.787853, "retransmits": 26, "snd_cwnd": 224440, "rtt": 2928, "omitted": false}, {"socket": 10, "start": 12.000408, "end": 13.001345, "seconds": 1.000937, "bytes": 55417488, "bits_per_second": 442924890.014901, "retransmits": 35, "snd_cwnd": 267880, "rtt": 2808, "omitted": false}], "sum": {"start": 12.000397, "end": 13.001333, "seconds": 1.000936, "bytes": 102259968, "bits_per_second": 817314711.81383, "retransmits": 61, "omitted": false}}, {"streams": [{"socket": 8, "start": 13.001333, "end": 14.000297, "seconds": 0.998964, "bytes": 47674568, "bits_per_second": 381792144.47624, "retransmits": 42, "snd_cwnd": 185344, "rtt": 2133, "omitted": false}, {"socket": 10, "start": 13.001345, "end": 14.000309, "seconds": 0.998964, "bytes": 54968320, "bits_per_second": 440202578.49641, "retransmits": 55, "snd_cwnd": 207064, "rtt": 2298, "omitted": false}], "sum": {"start": 13.001333, "end": 14.000297, "seconds": 0.998964, "bytes": 102642888, "bits_per_second": 821994828.033984, "retransmits": 97, "omitted": false}}, {"streams": [{"socket": 8, "start": 14.000297, "end": 15.00044, "seconds": 1.000143, "bytes": 49502776, "bits_per_second": 395965564.671619, "retransmits": 0, "snd_cwnd": 317112, "rtt": 4910, "omitted": false}, {"socket": 10, "start": 14.000309, "end": 15.000451, "seconds": 1.000142, "bytes": 54231040, "bits_per_second": 433786783.417021, "retransmits": 0, "snd_cwnd": 344624, "rtt": 5150, "omitted": false}], "sum": {"start": 14.000297, "end": 15.00044, "seconds": 1.000143, "bytes": 103733816, "bits_per_second": 829751831.048461, "retransmits": 0, "omitted": false}}, {"streams": [{"socket": 8, "start": 15.00044, "end": 16.00065, "seconds": 1.00021, "bytes": 54609392, "bits_per_second": 436783391.060309, "retransmits": 27, "snd_cwnd": 325800, "rtt": 3917, "omitted": false}, {"socket": 10, "start": 15.000451, "end": 16.000661, "seconds": 1.00021, "bytes": 48830400, "bits_per_second": 390561163.889745, "retransmits": 23, "snd_cwnd": 263536, "rtt": 3766, "omitted": false}], "sum": {"start": 15.00044, "end": 16.00065, "seconds": 1.00021, "bytes": 103439792, "bits_per_second": 827344554.950054, "retransmits": 50, "omitted": false}}, {"streams": [{"socket": 8, "start": 16.00065, "end": 17.000686, "seconds": 1.000036, "bytes": 53303640, "bits_per_second": 426413768.590313, "retransmits": 2, "snd_cwnd": 218648, "rtt": 2597, "omitted": false}, {"socket": 10, "start": 16.000661, "end": 17.000698, "seconds": 1.000037, "bytes": 51088384, "bits_per_second": 408691968.837432, "retransmits": 7, "snd_cwnd": 256296, "rtt": 2843, "omitted": false}], "sum": {"start": 16.00065, "end": 17.000686, "seconds": 1.000036, "bytes": 104392024, "bits_per_second": 835106127.172748, "retransmits": 9, "omitted": false}}, {"streams": [{"socket": 8, "start": 17.000686, "end": 18.000459, "seconds": 0.999773, "bytes": 48090144, "bits_per_second": 384808493.71057, "retransmits": 38, "snd_cwnd": 267880, "rtt": 4655, "omitted": false}, {"socket": 10, "start": 17.000698, "end": 18.000471, "seconds": 0.999773, "bytes": 54640640, "bits_per_second": 437224358.77467, "retransmits": 17, "snd_cwnd": 293944, "rtt": 4774, "omitted": false}], "sum": {"start": 17.000686, "end": 18.000459, "seconds": 0.999773, "bytes": 102730784, "bits_per_second": 822032852.48524, "retransmits": 55, "omitted": false}}, {"streams": [{"socket": 8, "start": 18.000459, "end": 19.000305, "seconds": 0.999846, "bytes": 49130640, "bits_per_second": 393105665.506458, "retransmits": 38, "snd_cwnd": 170864, "rtt": 2786, "omitted": false}, {"socket": 10, "start": 18.000471, "end": 19.000317, "seconds": 0.999846, "bytes": 52428800, "bits_per_second": 419495009.951121, "retransmits": 36, "snd_cwnd": 182448, "rtt": 2782, "omitted": false}], "sum": {"start": 18.000459, "end": 19.000305, "seconds": 0.999846, "bytes": 101559440, "bits_per_second": 812600675.457579, "retransmits": 74, "omitted": false}}, {"streams": [{"socket": 8, "start": 19.000305, "end": 20.000339, "seconds": 1.000034, "bytes": 49743792, "bits_per_second": 397936768.800784, "retransmits": 0, "snd_cwnd": 309872, "rtt": 2875, "omitted": false}, {"socket": 10, "start": 19.000317, "end": 20.000351, "seconds": 1.000034, "bytes": 52183040, "bits_per_second": 417450087.51649, "retransmits": 0, "snd_cwnd": 318560, "rtt": 2957, "omitted": false}], "sum": {"start": 19.000305, "end": 20.000339, "seconds": 1.000034, "bytes": 101926832, "bits_per_second": 815386856.317275, "retransmits": 0, "omitted": false}}], "end": {"streams": [{"sender": {"socket": 8, "start": 0, "end": 20.000339, "seconds": 20.000339, "bytes": 1075839536, "bits_per_second": 430328519.65986, "retransmits": 315, "max_snd_cwnd": 467704, "max_rtt": 4910, "min_rtt": 2133, "mean_rtt": 3242}, "receiver": {"socket": 8, "start": 0, "end": 20.000339, "seconds": 20.000339, "bytes": 1074754336, "bits_per_second": 429894447.018069}}, {"sender": {"socket": 10, "start": 0, "end": 20.000339, "seconds": 20.000339, "bytes": 991356528, "bits_per_second": 396535889.297694, "retransmits": 305, "max_snd_cwnd": 344624, "max_rtt": 5150, "min_rtt": 2255, "mean_rtt": 3308}, "receiver": {"socket": 10, "start": 0, "end": 20.000339, "seconds": 20.000339, "bytes": 990948592, "bits_per_second": 396372717.663708}}], "sum_sent": {"start": 0, "end": 20.000339, "seconds": 20.000339, "bytes": 2067196064, "bits_per_second": 826864408.957554, "retransmits": 620}, "sum_received": {"start": 0, "end": 20.000339, "seconds": 20.000339, "bytes": 2065702928, "bits_per_second": 826267164.681777}, "cpu_utilization_percent": {"host_total": 31.772889, "host_user": 3.03478, "host_system": 28.738129, "remote_total": 3.699928, "remote_user": 0.918368, "remote_system": 2.781558}}}