{"start": {"connected": [{"socket": 8, "local_host": "192.168.218.235", "local_port": 36444, "remote_host": "192.168.218.238", "remote_port": 5201}, {"socket": 10, "local_host": "192.168.218.235", "local_port": 36446, "remote_host": "192.168.218.238", "remote_port": 5201}], "version": "iperf 3.1.3", "system_info": "Linux hera 4.15.0-55-generic #60-Ubuntu SMP Tue Jul 2 18:22:20 UTC 2019 x86_64", "timestamp": {"time": "Sun, 11 Aug 2019 23:07:01 GMT", "timesecs": 1565564821}, "connecting_to": {"host": "192.168.218.238", "port": 5201}, "cookie": "hera.1565564821.642292.2cef52f841189", "tcp_mss_default": 1448, "test_start": {"protocol": "TCP", "num_streams": 2, "blksize": 8192, "omit": 0, "duration": 20, "bytes": 0, "blocks": 0, "reverse": 0}}, "intervals": [{"streams": [{"socket": 8, "start": 0, "end": 1.000592, "seconds": 1.000592, "bytes": 45123776, "bits_per_second": 360776630.640352, "retransmits": 79, "snd_cwnd": 183896, "rtt": 3303, "omitted": false}, {"socket": 10, "start": 0, "end": 1.000604, "seconds": 1.000604, "bytes": 56767096, "bits_per_second": 453862673.858783, "retransmits": 117, "snd_cwnd": 131768, "rtt": 3216, "omitted": false}], "sum": {"start": 0, "end": 1.000592, "seconds": 1.000592, "bytes": 101890872, "bits_per_second": 814644711.762761, "retransmits": 196, "omitted": false}}, {"streams": [{"socket": 8, "start": 1.000592, "end": 2.000309, "seconds": 0.999717, "bytes": 52592640, "bits_per_second": 420860224.644454, "retransmits": 0, "snd_cwnd": 324352, "rtt": 2689, "omitted": false}, {"socket": 10, "start": 1.000604, "end": 2.000321, "seconds": 0.999717, "bytes": 43875984, "bits_per_second": 351107236.349734, "retransmits": 0, "snd_cwnd": 280912, "rtt": 2593, "omitted": false}], "sum": {"start": 1.000592, "end": 2.000309, "seconds": 0.999717, "bytes": 96468624, "bits_per_second": 771967460.994188, "retransmits": 0, "omitted": false}}, {"streams": [{"socket": 8, "start": 2.000309, "end": 3.000205, "seconds": 0.999896, "bytes": 49838264, "bits_per_second": 398747657.087373, "retransmits": 27, "snd_cwnd": 305528, "rtt": 3745, "omitted": false}, {"socket": 10, "start": 2.000321, "end": 3.000217, "seconds": 0.999896, "bytes": 48705768, "bits_per_second": 389686652.122522, "retransmits": 0, "snd_cwnd": 377928, "rtt": 2813, "omitted": false}], "sum": {"start": 2.000309, "end": 3.000205, "seconds": 0.999896, "bytes": 98544032, "bits_per_second": 788434402.128113, "retransmits": 27, "omitted": false}}, {"streams": [{"socket": 8, "start": 3.000205, "end": 4.000352, "seconds": 1.000147, "bytes": 50130592, "bits_per_second": 400985749.286755, "retransmits": 45, "snd_cwnd": 289600, "rtt": 3464, "omitted": false}, {"socket": 10, "start": 3.000217, "end": 4.000363, "seconds": 1.000146, "bytes": 50938784, "bits_per_second": 407450819.966523, "retransmits": 45, "snd_cwnd": 253400, "rtt": 3304, "omitted": false}], "sum": {"start": 3.000205, "end": 4.000352, "seconds": 1.000147, "bytes": 101069376, "bits_per_second": 808436083.605492, "retransmits": 90, "omitted": false}}, {"streams": [{"socket": 8, "start": 4.000352, "end": 5.000814, "seconds": 1.000462, "bytes": 50026336, "bits_per_second": 400025853.971518, "retransmits": 21, "snd_cwnd": 224440, "rtt": 3899, "omitted": false}, {"socket": 10, "start": 4.000363, "end": 5.000879, "seconds": 1.000516, "bytes": 48952512, "bits_per_second": 391418148.579516, "retransmits": 1, "snd_cwnd": 278016, "rtt": 3640, "omitted": false}], "sum": {"start": 4.000352, "end": 5.000814, "seconds": 1.000462, "bytes": 98978848, "bits_per_second": 791465083.437594, "retransmits": 22, "omitted": false}}, {"streams": [{"socket": 8, "start": 5.000814, "end": 6.000233, "seconds": 0.999419, "bytes": 43475984, "bits_per_second": 348010074.928686, "retransmits": 29, "snd_cwnd": 214304, "rtt": 2625, "omitted": false}, {"socket": 10, "start": 5.000879, "end": 6.000245, "seconds": 0.999366, "bytes": 51200000, "bits_per_second": 409859832.690984, "retransmits": 57, "snd_cwnd": 237472, "rtt": 2531, "omitted": false}], "sum": {"start": 5.000814, "end": 6.000233, "seconds": 0.999419, "bytes": 94675984, "bits_per_second": 757848201.567723, "retransmits": 86, "omitted": false}}, {"streams": [{"socket": 8, "start": 6.000233, "end": 7.001048, "seconds": 1.000815, "bytes": 46745864, "bits_per_second": 373662409.008802, "retransmits": 6, "snd_cwnd": 282360, "rtt": 4288, "omitted": false}, {"socket": 10, "start": 6.000245, "end": 7.001061, "seconds": 1.000816, "bytes": 49889280, "bits_per_second": 398788785.761666, "retransmits": 12, "snd_cwnd": 296840, "rtt": 4192, "omitted": false}], "sum": {"start": 6.000233, "end": 7.001048, "seconds": 1.000815, "bytes": 96635144, "bits_per_second": 772451669.776657, "retransmits": 18, "omitted": false}}, {"streams": [{"socket": 8, "start": 7.001048, "end": 8.000696, "seconds": 0.999648, "bytes": 47128168, "bits_per_second": 377158068.12027, "retransmits": 26, "snd_cwnd": 279464, "rtt": 2224, "omitted": false}, {"socket": 10, "start": 7.001061, "end": 8.000709, "seconds": 0.999648, "bytes": 49233920, "bits_per_second": 394010108.390697, "retransmits": 33, "snd_cwnd": 286704, "rtt": 2167, "omitted": false}], "sum": {"start": 7.001048, "end": 8.000696, "seconds": 0.999648, "bytes": 96362088, "bits_per_second": 771168082.538567, "retransmits": 59, "omitted": false}}, {"streams": [{"socket": 8, "start": 8.000696, "end": 9.000552, "seconds": 0.999856, "bytes": 50448560, "bits_per_second": 403646607.05771, "retransmits": 10, "snd_cwnd": 283808, "rtt": 2259, "omitted": false}, {"socket": 10, "start": 8.000709, "end": 9.000565, "seconds": 0.999856, "bytes": 51445760, "bits_per_second": 411625356.036035, "retransmits": 13, "snd_cwnd": 292496, "rtt": 2158, "omitted": false}], "sum": {"start": 8.000696, "end": 9.000552, "seconds": 0.999856, "bytes": 101894320, "bits_per_second": 815271963.093745, "retransmits": 23, "omitted": false}}, {"streams": [{"socket": 8, "start": 9.000552, "end": 10.00061, "seconds": 1.000058, "bytes": 49394360, "bits_per_second": 395131987.745881, "retransmits": 22, "snd_cwnd": 227336, "rtt": 2995, "omitted": false}, {"socket": 10, "start": 9.000565, "end": 10.000623, "seconds": 1.000058, "bytes": 49971200, "bits_per_second": 399746345.102834, "retransmits": 19, "snd_cwnd": 230232, "rtt": 2884, "omitted": false}], "sum": {"start": 9.000552, "end": 10.00061, "seconds": 1.000058, "bytes": 99365560, "bits_per_second": 794878428.150148, "retransmits": 41, "omitted": false}}, {"streams": [{"socket": 8, "start": 10.00061, "end": 11.000258, "seconds": 0.999648, "bytes": 48648400, "bits_per_second": 389324205.454839, "retransmits": 18, "snd_cwnd": 253400, "rtt": 2873, "omitted": false}, {"socket": 10, "start": 10.000623, "end": 11.00027, "seconds": 0.999647, "bytes": 49315840, "bits_per_second": 394666075.768731, "retransmits": 14, "snd_cwnd": 254848, "rtt": 3006, "omitted": false}], "sum": {"start": 10.00061, "end": 11.000258, "seconds": 0.999648, "bytes": 97964240, "bits_per_second": 783989810.579323, "retransmits": 32, "omitted": false}}, {"streams": [{"socket": 8, "start": 11.000258, "end": 12.001201, "seconds": 1.000943, "bytes": 45118568, "bits_per_second": 360608509.835476, "retransmits": 33, "snd_cwnd": 250504, "rtt": 7670, "omitted": false}, {"socket": 10, "start": 11.00027, "end": 12.001215, "seconds": 1.000945, "bytes": 45711360, "bits_per_second": 365345595.07576, "retransmits": 56, "snd_cwnd": 251952, "rtt": 8157, "omitted": false}], "sum": {"start": 11.000258, "end": 12.001201, "seconds": 1.000943, "bytes": 90829928, "bits_per_second": 725954888.119312, "retransmits": 89, "omitted": false}}, {"streams": [{"socket": 8, "start": 12.001201, "end": 13.000335, "seconds": 0.999134, "bytes": 49192224, "bits_per_second": 393878865.999717, "retransmits": 0, "snd_cwnd": 359104, "rtt": 3221, "omitted": false}, {"socket": 10, "start": 12.001215, "end": 13.000348, "seconds": 0.999133, "bytes": 49889280, "bits_per_second": 399460623.640332, "retransmits": 0, "snd_cwnd": 363448, "rtt": 2864, "omitted": false}], "sum": {"start": 12.001201, "end": 13.000335, "seconds": 0.999134, "bytes": 99081504, "bits_per_second": 793339013.033167, "retransmits": 0, "omitted": false}}, {"streams": [{"socket": 8, "start": 13.000335, "end": 14.001277, "seconds": 1.000942, "bytes": 48726648, "bits_per_second": 389446328.749429, "retransmits": 22, "snd_cwnd": 315664, "rtt": 2460, "omitted": false}, {"socket": 10, "start": 13.000348, "end": 14.001289, "seconds": 1.000941, "bytes": 49315840, "bits_per_second": 394155804.358263, "retransmits": 25, "snd_cwnd": 318560, "rtt": 2821, "omitted": false}], "sum": {"start": 13.000335, "end": 14.001277, "seconds": 1.000942, "bytes": 98042488, "bits_per_second": 783601757.565183, "retransmits": 47, "omitted": false}}, {"streams": [{"socket": 8, "start": 14.001277, "end": 15.001485, "seconds": 1.000208, "bytes": 52490208, "bits_per_second": 419834380.012151, "retransmits": 0, "snd_cwnd": 409784, "rtt": 2824, "omitted": false}, {"socket": 10, "start": 14.001289, "end": 15.001496, "seconds": 1.000207, "bytes": 47822008, "bits_per_second": 382496907.287581, "retransmits": 1, "snd_cwnd": 302632, "rtt": 3301, "omitted": false}], "sum": {"start": 14.001277, "end": 15.001485, "seconds": 1.000208, "bytes": 100312216, "bits_per_second": 802330922.598077, "retransmits": 1, "omitted": false}}, {"streams": [{"socket": 8, "start": 15.001485, "end": 16.000384, "seconds": 0.998899, "bytes": 58327040, "bits_per_second": 467130638.773712, "retransmits": 18, "snd_cwnd": 385168, "rtt": 2136, "omitted": false}, {"socket": 10, "start": 15.001496, "end": 16.000449, "seconds": 0.998953, "bytes": 44122624, "bits_per_second": 353350913.651326, "retransmits": 18, "snd_cwnd": 308424, "rtt": 2252, "omitted": false}], "sum": {"start": 15.001485, "end": 16.000384, "seconds": 0.998899, "bytes": 102449664, "bits_per_second": 820500697.214743, "retransmits": 36, "omitted": false}}, {"streams": [{"socket": 8, "start": 16.000384, "end": 17.000104, "seconds": 0.99972, "bytes": 55296000, "bits_per_second": 442491854.979931, "retransmits": 39, "snd_cwnd": 231680, "rtt": 2424, "omitted": false}, {"socket": 10, "start": 16.000449, "end": 17.000167, "seconds": 0.999718, "bytes": 43457376, "bits_per_second": 347757092.602487, "retransmits": 55, "snd_cwnd": 147696, "rtt": 2437, "omitted": false}], "sum": {"start": 16.000384, "end": 17.000104, "seconds": 0.99972, "bytes": 98753376, "bits_per_second": 790248201.167727, "retransmits": 94, "omitted": false}}, {"streams": [{"socket": 8, "start": 17.000104, "end": 18.001259, "seconds": 1.001155, "bytes": 55541760, "bits_per_second": 443821510.71606, "retransmits": 0, "snd_cwnd": 359104, "rtt": 2321, "omitted": false}, {"socket": 10, "start": 17.000167, "end": 18.001271, "seconds": 1.001104, "bytes": 39761464, "bits_per_second": 317740889.060785, "retransmits": 0, "snd_cwnd": 273672, "rtt": 2793, "omitted": false}], "sum": {"start": 17.000104, "end": 18.001259, "seconds": 1.001155, "bytes": 95303224, "bits_per_second": 761546282.50511, "retransmits": 0, "omitted": false}}, {"streams": [{"socket": 8, "start": 18.001259, "end": 19.000419, "seconds": 0.99916, "bytes": 54804480, "bits_per_second": 438804413.176293, "retransmits": 0, "snd_cwnd": 438744, "rtt": 2924, "omitted": false}, {"socket": 10, "start": 18.001271, "end": 19.000431, "seconds": 0.99916, "bytes": 43320432, "bits_per_second": 346854878.985445, "retransmits": 0, "snd_cwnd": 359104, "rtt": 2901, "omitted": false}], "sum": {"start": 18.001259, "end": 19.000419, "seconds": 0.99916, "bytes": 98124912, "bits_per_second": 785659209.395572, "retransmits": 0, "omitted": false}}, {"streams": [{"socket": 8, "start": 19.000419, "end": 20.000313, "seconds": 0.999894, "bytes": 54722560, "bits_per_second": 437826931.803363, "retransmits": 85, "snd_cwnd": 289600, "rtt": 2184, "omitted": false}, {"socket": 10, "start": 19.000431, "end": 20.000325, "seconds": 0.999894, "bytes": 46037712, "bits_per_second": 368340687.752949, "retransmits": 83, "snd_cwnd": 249056, "rtt": 2344, "omitted": false}], "sum": {"start": 19.000419, "end": 20.000313, "seconds": 0.999894, "bytes": 100760272, "bits_per_second": 806167707.384894, "retransmits": 168, "omitted": false}}], "end": {"streams": [{"sender": {"socket": 8, "start": 0, "end": 20.000313, "seconds": 20.000313, "bytes": 1007772432, "bits_per_second": 403102668.169951, "retransmits": 480, "max_snd_cwnd": 438744, "max_rtt": 7670, "min_rtt": 2136, "mean_rtt": 3126}, "receiver": {"socket": 8, "start": 0, "end": 20.000313, "seconds": 20.000313, "bytes": 1007088096, "bits_per_second": 402828938.051161}}, {"sender": {"socket": 10, "start": 0, "end": 20.000313, "seconds": 20.000313, "bytes": 959734240, "bits_per_second": 383887691.897153, "retransmits": 549, "max_snd_cwnd": 377928, "max_rtt": 8157, "min_rtt": 2158, "mean_rtt": 3118}, "receiver": {"socket": 10, "start": 0, "end": 20.000313, "seconds": 20.000313, "bytes": 958572448, "bits_per_second": 383422982.36533}}], "sum_sent": {"start": 0, "end": 20.000313, "seconds": 20.000313, "bytes": 1967506672, "bits_per_second": 786990360.067104, "retransmits": 1029}, "sum_received": {"start": 0, "end": 20.000313, "seconds": 20.000313, "bytes": 1965660544, "bits_per_second": 786251920.416491}, "cpu_utilization_percent": {"host_total": 31.147482, "host_user": 3.430228, "host_system": 27.717264, "remote_total": 5.773126, "remote_user": 1.379012, "remote_system": 4.394115}}}