{"start": {"connected": [{"socket": 8, "local_host": "192.168.218.235", "local_port": 35770, "remote_host": "192.168.218.238", "remote_port": 5201}, {"socket": 10, "local_host": "192.168.218.235", "local_port": 35772, "remote_host": "192.168.218.238", "remote_port": 5201}], "version": "iperf 3.1.3", "system_info": "Linux hera 4.15.0-55-generic #60-Ubuntu SMP Tue Jul 2 18:22:20 UTC 2019 x86_64", "timestamp": {"time": "Sun, 11 Aug 2019 20:28:02 GMT", "timesecs": 1565555282}, "connecting_to": {"host": "192.168.218.238", "port": 5201}, "cookie": "hera.1565555282.014197.0b413cbf7d080", "tcp_mss_default": 1448, "test_start": {"protocol": "TCP", "num_streams": 2, "blksize": 8192, "omit": 0, "duration": 20, "bytes": 0, "blocks": 0, "reverse": 0}}, "intervals": [{"streams": [{"socket": 8, "start": 0, "end": 1.000056, "seconds": 1.000056, "bytes": 54224752, "bits_per_second": 433773712.367644, "retransmits": 23, "snd_cwnd": 272224, "rtt": 2448, "omitted": false}, {"socket": 10, "start": 0, "end": 1.000123, "seconds": 1.000123, "bytes": 48462712, "bits_per_second": 387654005.258768, "retransmits": 27, "snd_cwnd": 256296, "rtt": 2302, "omitted": false}], "sum": {"start": 0, "end": 1.000056, "seconds": 1.000056, "bytes": 102687464, "bits_per_second": 821453687.292083, "retransmits": 50, "omitted": false}}, {"streams": [{"socket": 8, "start": 1.000056, "end": 2.000407, "seconds": 1.000351, "bytes": 52101120, "bits_per_second": 416662731.31927, "retransmits": 40, "snd_cwnd": 249056, "rtt": 2823, "omitted": false}, {"socket": 10, "start": 1.000123, "end": 2.000419, "seconds": 1.000296, "bytes": 49178824, "bits_per_second": 393314125.443498, "retransmits": 36, "snd_cwnd": 243264, "rtt": 2755, "omitted": false}], "sum": {"start": 1.000056, "end": 2.000407, "seconds": 1.000351, "bytes": 101279944, "bits_per_second": 809955296.448573, "retransmits": 76, "omitted": false}}, {"streams": [{"socket": 8, "start": 2.000407, "end": 3.000501, "seconds": 1.000094, "bytes": 52346880, "bits_per_second": 418735605.432514, "retransmits": 0, "snd_cwnd": 366344, "rtt": 4187, "omitted": false}, {"socket": 10, "start": 2.000419, "end": 3.000512, "seconds": 1.000093, "bytes": 50975392, "bits_per_second": 407765220.666238, "retransmits": 0, "snd_cwnd": 356208, "rtt": 3911, "omitted": false}], "sum": {"start": 2.000407, "end": 3.000501, "seconds": 1.000094, "bytes": 103322272, "bits_per_second": 826500340.050503, "retransmits": 0, "omitted": false}}, {"streams": [{"socket": 8, "start": 3.000501, "end": 4.001847, "seconds": 1.001346, "bytes": 52592640, "bits_per_second": 420175617.032607, "retransmits": 14, "snd_cwnd": 348968, "rtt": 3272, "omitted": false}, {"socket": 10, "start": 3.000512, "end": 4.001859, "seconds": 1.001347, "bytes": 51062768, "bits_per_second": 407952702.467808, "retransmits": 19, "snd_cwnd": 341728, "rtt": 3248, "omitted": false}], "sum": {"start": 3.000501, "end": 4.001847, "seconds": 1.001346, "bytes": 103655408, "bits_per_second": 828128708.031516, "retransmits": 33, "omitted": false}}, {"streams": [{"socket": 8, "start": 4.001847, "end": 5.000113, "seconds": 0.998266, "bytes": 52592640, "bits_per_second": 421471960.102631, "retransmits": 7, "snd_cwnd": 348968, "rtt": 3007, "omitted": false}, {"socket": 10, "start": 4.001859, "end": 5.000125, "seconds": 0.998266, "bytes": 51705120, "bits_per_second": 414359466.909091, "retransmits": 12, "snd_cwnd": 346072, "rtt": 2940, "omitted": false}], "sum": {"start": 4.001847, "end": 5.000113, "seconds": 0.998266, "bytes": 104297760, "bits_per_second": 835831427.011723, "retransmits": 19, "omitted": false}}, {"streams": [{"socket": 8, "start": 5.000113, "end": 6.000433, "seconds": 1.00032, "bytes": 51281920, "bits_per_second": 410124137.610618, "retransmits": 6, "snd_cwnd": 347520, "rtt": 3804, "omitted": false}, {"socket": 10, "start": 5.000125, "end": 6.000446, "seconds": 1.000321, "bytes": 50915632, "bits_per_second": 407194285.626003, "retransmits": 14, "snd_cwnd": 346072, "rtt": 3804, "omitted": false}], "sum": {"start": 5.000113, "end": 6.000433, "seconds": 1.00032, "bytes": 102197552, "bits_per_second": 817318908.494774, "retransmits": 20, "omitted": false}}, {"streams": [{"socket": 8, "start": 6.000433, "end": 7.000163, "seconds": 0.99973, "bytes": 51118080, "bits_per_second": 409055039.795782, "retransmits": 8, "snd_cwnd": 344624, "rtt": 2640, "omitted": false}, {"socket": 10, "start": 6.000446, "end": 7.000175, "seconds": 0.999729, "bytes": 50867368, "bits_per_second": 407049287.704252, "retransmits": 12, "snd_cwnd": 346072, "rtt": 2399, "omitted": false}], "sum": {"start": 6.000433, "end": 7.000163, "seconds": 0.99973, "bytes": 101985448, "bits_per_second": 816103842.128474, "retransmits": 20, "omitted": false}}, {"streams": [{"socket": 8, "start": 7.000163, "end": 8.00032, "seconds": 1.000157, "bytes": 51281920, "bits_per_second": 410191009.470274, "retransmits": 14, "snd_cwnd": 338832, "rtt": 3257, "omitted": false}, {"socket": 10, "start": 7.000175, "end": 8.000331, "seconds": 1.000156, "bytes": 51281920, "bits_per_second": 410191400.597918, "retransmits": 15, "snd_cwnd": 337384, "rtt": 3436, "omitted": false}], "sum": {"start": 7.000163, "end": 8.00032, "seconds": 1.000157, "bytes": 102563840, "bits_per_second": 820382018.940548, "retransmits": 29, "omitted": false}}, {"streams": [{"socket": 8, "start": 8.00032, "end": 9.000378, "seconds": 1.000058, "bytes": 44973648, "bits_per_second": 359768254.793588, "retransmits": 1, "snd_cwnd": 321456, "rtt": 3058, "omitted": false}, {"socket": 10, "start": 8.000331, "end": 9.00039, "seconds": 1.000059, "bytes": 58408960, "bits_per_second": 467244052.883531, "retransmits": 0, "snd_cwnd": 428608, "rtt": 3163, "omitted": false}], "sum": {"start": 8.00032, "end": 9.000378, "seconds": 1.000058, "bytes": 103382608, "bits_per_second": 827012753.249851, "retransmits": 1, "omitted": false}}, {"streams": [{"socket": 8, "start": 9.000378, "end": 10.000162, "seconds": 0.999784, "bytes": 44182824, "bits_per_second": 353538958.972167, "retransmits": 11, "snd_cwnd": 233128, "rtt": 2452, "omitted": false}, {"socket": 10, "start": 9.00039, "end": 10.000174, "seconds": 0.999784, "bytes": 58081280, "bits_per_second": 464750629.497357, "retransmits": 13, "snd_cwnd": 398200, "rtt": 2445, "omitted": false}], "sum": {"start": 9.000378, "end": 10.000162, "seconds": 0.999784, "bytes": 102264104, "bits_per_second": 818289588.469525, "retransmits": 24, "omitted": false}}, {"streams": [{"socket": 8, "start": 10.000162, "end": 11.000629, "seconds": 1.000467, "bytes": 39644792, "bits_per_second": 317010348.095077, "retransmits": 10, "snd_cwnd": 272224, "rtt": 2352, "omitted": false}, {"socket": 10, "start": 10.000174, "end": 11.000642, "seconds": 1.000468, "bytes": 61685760, "bits_per_second": 493255228.823218, "retransmits": 14, "snd_cwnd": 392408, "rtt": 2403, "omitted": false}], "sum": {"start": 10.000162, "end": 11.000629, "seconds": 1.000467, "bytes": 101330552, "bits_per_second": 810266164.649982, "retransmits": 24, "omitted": false}}, {"streams": [{"socket": 8, "start": 11.000629, "end": 12.000158, "seconds": 0.999529, "bytes": 39123728, "bits_per_second": 313137273.043813, "retransmits": 6, "snd_cwnd": 208512, "rtt": 3478, "omitted": false}, {"socket": 10, "start": 11.000642, "end": 12.000171, "seconds": 0.999529, "bytes": 61931520, "bits_per_second": 495685685.017165, "retransmits": 21, "snd_cwnd": 356208, "rtt": 3332, "omitted": false}], "sum": {"start": 11.000629, "end": 12.000158, "seconds": 0.999529, "bytes": 101055248, "bits_per_second": 808822839.824626, "retransmits": 27, "omitted": false}}, {"streams": [{"socket": 8, "start": 12.000158, "end": 13.000519, "seconds": 1.000361, "bytes": 40270112, "bits_per_second": 322044648.91861, "retransmits": 5, "snd_cwnd": 263536, "rtt": 2484, "omitted": false}, {"socket": 10, "start": 12.000171, "end": 13.000531, "seconds": 1.00036, "bytes": 61194240, "bits_per_second": 489377738.115102, "retransmits": 19, "snd_cwnd": 370688, "rtt": 2105, "omitted": false}], "sum": {"start": 12.000158, "end": 13.000519, "seconds": 1.000361, "bytes": 101464352, "bits_per_second": 811421920.495137, "retransmits": 24, "omitted": false}}, {"streams": [{"socket": 8, "start": 13.000519, "end": 14.000551, "seconds": 1.000032, "bytes": 42941272, "bits_per_second": 343519201.21778, "retransmits": 45, "snd_cwnd": 189688, "rtt": 3582, "omitted": false}, {"socket": 10, "start": 13.000531, "end": 14.000564, "seconds": 1.000033, "bytes": 54886400, "bits_per_second": 439076648.919725, "retransmits": 63, "snd_cwnd": 221544, "rtt": 3646, "omitted": false}], "sum": {"start": 13.000519, "end": 14.000551, "seconds": 1.000032, "bytes": 97827672, "bits_per_second": 782596373.540938, "retransmits": 108, "omitted": false}}, {"streams": [{"socket": 8, "start": 14.000551, "end": 15.000681, "seconds": 1.00013, "bytes": 46193264, "bits_per_second": 369498100.109455, "retransmits": 23, "snd_cwnd": 217200, "rtt": 3014, "omitted": false}, {"socket": 10, "start": 14.000564, "end": 15.000693, "seconds": 1.000129, "bytes": 51527680, "bits_per_second": 412168276.700989, "retransmits": 37, "snd_cwnd": 234576, "rtt": 2935, "omitted": false}], "sum": {"start": 14.000551, "end": 15.000681, "seconds": 1.00013, "bytes": 97720944, "bits_per_second": 781665983.787213, "retransmits": 60, "omitted": false}}, {"streams": [{"socket": 8, "start": 15.000681, "end": 16.000727, "seconds": 1.000046, "bytes": 48838816, "bits_per_second": 390692550.365994, "retransmits": 7, "snd_cwnd": 254848, "rtt": 3329, "omitted": false}, {"socket": 10, "start": 15.000693, "end": 16.000739, "seconds": 1.000046, "bytes": 51527680, "bits_per_second": 412202472.591531, "retransmits": 11, "snd_cwnd": 267880, "rtt": 3363, "omitted": false}], "sum": {"start": 15.000681, "end": 16.000727, "seconds": 1.000046, "bytes": 100366496, "bits_per_second": 802895022.957525, "retransmits": 18, "omitted": false}}, {"streams": [{"socket": 8, "start": 16.000727, "end": 17.001065, "seconds": 1.000338, "bytes": 50271424, "bits_per_second": 402035472.834275, "retransmits": 4, "snd_cwnd": 273672, "rtt": 3038, "omitted": false}, {"socket": 10, "start": 16.000739, "end": 17.001077, "seconds": 1.000338, "bytes": 52101120, "bits_per_second": 416668193.181539, "retransmits": 3, "snd_cwnd": 279464, "rtt": 2947, "omitted": false}], "sum": {"start": 16.000727, "end": 17.001065, "seconds": 1.000338, "bytes": 102372544, "bits_per_second": 818703566.707949, "retransmits": 7, "omitted": false}}, {"streams": [{"socket": 8, "start": 17.001065, "end": 18.0005, "seconds": 0.999435, "bytes": 50084440, "bits_per_second": 400902050.518467, "retransmits": 15, "snd_cwnd": 278016, "rtt": 2144, "omitted": false}, {"socket": 10, "start": 17.001077, "end": 18.000513, "seconds": 0.999436, "bytes": 51609600, "bits_per_second": 413109736.030796, "retransmits": 14, "snd_cwnd": 285256, "rtt": 2661, "omitted": false}], "sum": {"start": 17.001065, "end": 18.0005, "seconds": 0.999435, "bytes": 101694040, "bits_per_second": 814012279.292871, "retransmits": 29, "omitted": false}}, {"streams": [{"socket": 8, "start": 18.0005, "end": 19.000551, "seconds": 1.000051, "bytes": 49630200, "bits_per_second": 397021343.345386, "retransmits": 13, "snd_cwnd": 309872, "rtt": 2295, "omitted": false}, {"socket": 10, "start": 18.000513, "end": 19.000565, "seconds": 1.000052, "bytes": 50462720, "bits_per_second": 403680778.590514, "retransmits": 5, "snd_cwnd": 317112, "rtt": 2468, "omitted": false}], "sum": {"start": 18.0005, "end": 19.000551, "seconds": 1.000051, "bytes": 100092920, "bits_per_second": 800702506.896249, "retransmits": 18, "omitted": false}}, {"streams": [{"socket": 8, "start": 19.000551, "end": 20.00011, "seconds": 0.999559, "bytes": 49609808, "bits_per_second": 397053499.45773, "retransmits": 14, "snd_cwnd": 299736, "rtt": 3094, "omitted": false}, {"socket": 10, "start": 19.000565, "end": 20.000123, "seconds": 0.999558, "bytes": 50298880, "bits_per_second": 402568986.782468, "retransmits": 14, "snd_cwnd": 305528, "rtt": 3286, "omitted": false}], "sum": {"start": 19.000551, "end": 20.00011, "seconds": 0.999559, "bytes": 99908688, "bits_per_second": 799622006.128919, "retransmits": 28, "omitted": false}}], "end": {"streams": [{"sender": {"socket": 8, "start": 0, "end": 20.00011, "seconds": 20.00011, "bytes": 963304280, "bits_per_second": 385319589.864235, "retransmits": 266, "max_snd_cwnd": 366344, "max_rtt": 4187, "min_rtt": 2144, "mean_rtt": 2987}, "receiver": {"socket": 8, "start": 0, "end": 20.00011, "seconds": 20.00011, "bytes": 962382024, "bits_per_second": 384950689.495943}}, {"sender": {"socket": 10, "start": 0, "end": 20.00011, "seconds": 20.00011, "bytes": 1068165576, "bits_per_second": 427263877.257365, "retransmits": 349, "max_snd_cwnd": 428608, "max_rtt": 3911, "min_rtt": 2105, "mean_rtt": 2977}, "receiver": {"socket": 10, "start": 0, "end": 20.00011, "seconds": 20.00011, "bytes": 1067610400, "bits_per_second": 427041808.080405}}], "sum_sent": {"start": 0, "end": 20.00011, "seconds": 20.00011, "bytes": 2031469856, "bits_per_second": 812583467.121601, "retransmits": 615}, "sum_received": {"start": 0, "end": 20.00011, "seconds": 20.00011, "bytes": 2029992424, "bits_per_second": 811992497.576347}, "cpu_utilization_percent": {"host_total": 33.978029, "host_user": 3.878601, "host_system": 30.099438, "remote_total": 4.884168, "remote_user": 1.207288, "remote_system": 3.676878}}}